Metadata-Version: 2.1
Name: EnthalpyGradients
Version: 1.0
Summary: Library for calculation of daily enthalpy gradients
Home-page: https://github.com/JIMENOFONSECA/EnthalpyGradients
Author: Jimeno A. Fonseca
Author-email: fonseca.jimeno@gmail.com
License: MIT
Download-URL: https://github.com/JIMENOFONSECA/EnthalpyGradients/archive/1.0.tar.gz
Platform: UNKNOWN
Classifier: Programming Language :: Python :: 3
Classifier: License :: OSI Approved :: MIT License
Classifier: Operating System :: OS Independent
Requires-Python: >=3.6
